msgoverhttp/LICENSE
msgoverhttp/__init__.py
msgoverhttp-0.1.0.dist-info/WHEEL
msgoverhttp-0.1.0.dist-info/METADATA
msgoverhttp-0.1.0.dist-info/RECORD
