Metadata-Version: 2.1
Name: msgoverhttp
Version: 0.1.0
Summary: Let's find some podcasts!
Author-email: xiao long <admin@coolink.pub>
Classifier: License :: OSI Approved :: Apache Software License
